vmake/__init__.py
vmake/vmake.py
vmake-0.1.2.dist-info/LICENSE.txt
vmake-0.1.2.dist-info/METADATA
vmake-0.1.2.dist-info/WHEEL
vmake-0.1.2.dist-info/entry_points.txt
vmake-0.1.2.dist-info/top_level.txt
vmake-0.1.2.dist-info/RECORD
