Metadata-Version: 2.1
Name: vmake
Version: 0.1.2
Summary: Wrapper for "make", creating VSCode hyperlinks
Home-page: https://github.com/patrislav1/vmake
Author: Patrick Huesmann
Author-email: info@patrick-huesmann.de
License: BSD
Keywords: vscode make gcc hyperlinks
Platform: UNKNOWN
Classifier: Programming Language :: Python :: 3.6
Classifier: Operating System :: OS Independent
Classifier: Environment :: Console
Classifier: License :: OSI Approved :: BSD License
Classifier: Intended Audience :: Developers
Classifier: Development Status :: 3 - Alpha
Requires-Python: >=3.6
